{
    "output_dir": "outputs/sim_3stage_sarm_v4_noise005_short",
    "job_name": "sim_3stage_sarm_v4_noise005_short",
    "resume": false, "seed": 1000, "num_workers": 12, "batch_size": 32, "steps": 3500,
    "eval_freq": 0, "log_freq": 50, "save_checkpoint": true, "save_freq": 1000,
    "use_policy_training_preset": true,
    "wandb": {"enable": false},
    "dataset": {"repo_id": "domrachev03/sim_3stage_v4_success_train_fs", "use_imagenet_stats": false},
    "policy": {
        "type": "sarm_ext", "annotation_mode": "dual", "device": "cuda", "push_to_hub": false,
        "image_keys": ["observation.images.wrist"],
        "state_key": "observation.state",
        "n_obs_steps": 8, "frame_gap": 20, "max_rewind_steps": 4,
        "batch_size": 32, "clip_batch_size": 32,
        "stage_loss_weight": 3.0,
        "state_noise_std": 0.05
    }
}
